minblepy-19.dist-info/RECORD
minblepy-19.dist-info/WHEEL
minblepy-19.dist-info/top_level.txt
minblepy-19.dist-info/METADATA
minblepy-19.dist-info/licenses/COPYING
minBlepy/paste.py
minBlepy/__init__.py
minBlepy/warmup.py
minBlepy/minblep.py
minBlepy/paste_turbo/pasteminbleps.pyx
minBlepy/paste_turbo/pasteminbleps.cpython-312-i386-linux-gnu.so
minBlepy/paste_turbo/__init__.py
minBlepy/paste_turbo/pasteminbleps.pyxbld
