Metadata-Version: 2.4
Name: minBlepy
Version: 19
Summary: MinBLEPs library including fast naive waveform conversion
Home-page: https://github.com/combatopera/minBlepy
Author: Andrzej Cichocki and contributors
Author-email: 3613868+combatopera@users.noreply.github.com
License-File: COPYING
Requires-Dist: lagoon>=21
Requires-Dist: numpy>=2.0.2
Requires-Dist: pyrbo>=19
Dynamic: author
Dynamic: author-email
Dynamic: description
Dynamic: description-content-type
Dynamic: home-page
Dynamic: license-file
Dynamic: requires-dist
Dynamic: summary
